newz/__init__.py
newz/articles.py
newz/finance.py
newz/forecast.py
newz/newz.py
newz/newzconfig.py
newz/weather.py
newz-1.0.2.dist-info/LICENSE
newz-1.0.2.dist-info/METADATA
newz-1.0.2.dist-info/WHEEL
newz-1.0.2.dist-info/entry_points.txt
newz-1.0.2.dist-info/top_level.txt
newz-1.0.2.dist-info/RECORD
