Metadata-Version: 2.1
Name: newz
Version: 1.0.2
Summary: Local news delivered straight to your terminal
Home-page: UNKNOWN
Author: Michael Leone
Author-email: msleone90@gmail.com
License: MIT
Platform: UNKNOWN
Classifier: License :: OSI Approved :: MIT License
Classifier: Programming Language :: Python :: 3
Classifier: Programming Language :: Python :: 3.7
